cbicqc/__init__.py
cbicqc/__main__.py
cbicqc/calendar.py
cbicqc/cbicqc.py
cbicqc/dicomqr.py
cbicqc/graphics.py
cbicqc/metrics.py
cbicqc/moco.py
cbicqc/report.py
cbicqc/rois.py
cbicqc/summary.py
cbicqc/timeseries.py
cbicqc/templates/MNI-maxprob-thr25-2mm.nii.gz
cbicqc/templates/MNI152_T1_2mm.nii.gz
cbicqc/templates/MNI152_T1_2mm_brain.nii.gz
cbicqc/templates/MNI152_T1_2mm_brain_mask.nii.gz
cbicqc/templates/MNI152_T1_2mm_brain_mask_fill.nii.gz
cbicqc/templates/MNI152_T1_2mm_head_mask.nii.gz
cbicqc/templates/MNI152_T1_2mm_head_mask_fill.nii.gz
cbicqc/templates/Makefile
cbicqc/templates/brain_mask.nii.gz
cbicqc/templates/fbirn_labels.nii.gz
cbicqc/templates/fbirn_sphere.nii.gz
cbicqc/templates/fbirn_template.nii.gz
cbicqc/templates/mni_brain_mask.nii.gz
cbicqc/templates/mni_head_mask.nii.gz
cbicqc/templates/mni_labels.nii.gz
cbicqc/templates/mni_template.nii.gz
cbicqc/templates/temp.nii.gz
cbicqc-2022.2.28.1.data/scripts/cbicqc_incoming.py
cbicqc-2022.2.28.1.dist-info/COPYING.txt
cbicqc-2022.2.28.1.dist-info/LICENSE.md
cbicqc-2022.2.28.1.dist-info/METADATA
cbicqc-2022.2.28.1.dist-info/WHEEL
cbicqc-2022.2.28.1.dist-info/entry_points.txt
cbicqc-2022.2.28.1.dist-info/top_level.txt
cbicqc-2022.2.28.1.dist-info/RECORD
