Metadata-Version: 2.1
Name: cbicqc
Version: 2022.2.28.1
Summary: MRI phantom quality control tool
Home-page: https://github.com/jmtyszka/cbicqc
Author: Julian Michael Tyszka
Author-email: jmt@caltech.edu
License: UNKNOWN
Project-URL: Bug Reports, https://github.com/jmtyszka/cbicqc/issues
Project-URL: Funding, http://conte.caltech.edu/
Project-URL: Source, https://github.com/jmtyszka/cbicqc/
Keywords: neuroimaging MRI DICOM BIDS QC
Platform: UNKNOWN
Classifier: Development Status :: 3 - Alpha
Classifier: Intended Audience :: Science/Research
Classifier: Topic :: Scientific/Engineering :: Image Processing
Classifier: License :: OSI Approved :: MIT License
Classifier: Programming Language :: Python :: 3.7
Classifier: Programming Language :: Python :: 3.8
Classifier: Programming Language :: Python :: 3.9
Requires-Python: >=3.7, <4
License-File: LICENSE.md
License-File: COPYING.txt
Requires-Dist: pydicom (>=1.2.2)
Requires-Dist: numpy (>=1.15.2)
Requires-Dist: scipy
Requires-Dist: pybids
Requires-Dist: nibabel
Requires-Dist: nipype
Requires-Dist: reportlab
Requires-Dist: scikit-image
Requires-Dist: scikit-learn (>=0.24)
Requires-Dist: statsmodels (>=0.9.0)
Requires-Dist: pynetdicom (>=1.2.0)
Requires-Dist: pandas
